sky_report/__init__.py
sky_report/sky_report.py
sky_report-1.0.0.dist-info/METADATA
sky_report-1.0.0.dist-info/WHEEL
sky_report-1.0.0.dist-info/top_level.txt
sky_report-1.0.0.dist-info/zip-safe
sky_report-1.0.0.dist-info/RECORD
