Metadata-Version: 2.1
Name: sky-report
Version: 1.0.0
Summary: pytest测试报告
Home-page: http://www.baidu.com/
Author: baidu
Author-email: baidu@163.com
License: MIT
Keywords: pytest sky_report
Requires-Dist: jinja2 (>=2.10)
